[
    {
        "outputFileName": "wwwroot/css/site.min.css",
        "inputFiles": [
            "wwwroot/css/site.css"
        ]
    },
    {
        "outputFileName": "wwwroot/css/materialize.min.css",
        "inputFiles": [
            "wwwroot/css/materialize.css"
        ]
    },
    {
        "outputFileName": "wwwroot/js/materialize.min.js",
        "inputFiles": [
            "wwwroot/js/materialize.js"
        ],
        "minify": {
            "enabled": true,
            "renameLocals": true
        },
        "sourceMap": false
    },
    {
        "outputFileName": "wwwroot/js/site.min.js",
        "inputFiles": [
            "wwwroot/js/site.js"
        ],
        "minify": {
            "enabled": true,
            "renameLocals": true
        },
        "sourceMap": false
    }
]